{
    "items": [
      {
        "day": 8,
        "month": "outubro",
        "imageSrc": "image1.png",
        "altText": "Image 1 mobile",
        "descriptionTitle": "Job Insights 1",
        "descriptionSubtitle": "Terça Feira, 27 de Março às 13:00",
        "logoSrc": "image1logo.png",
        "logoAlt": "ImageLogo 1 mobile",
        "oppPlaceTitle": "AE IST",
        "oppPlaceSubtitle": "Lisboa, PT",
        "moreInfoLink": "https://www.youtube.com/watch?v=dQw4w9WgXcQ",
        "startTime": "10:00",
        "endTime": "14:00"
      },      
      {
        "day": 8,
        "month": "outubro",
        "imageSrc": "image2.png",
        "altText": "Image 2 mobile",
        "descriptionTitle": "Job Insights 2",
        "descriptionSubtitle": "Terça Feira, 27 de Outubro às 13:00",
        "logoSrc": "image2logo.png",
        "logoAlt": "ImageLogo 2 mobile",
        "oppPlaceTitle": "AE IST",
        "oppPlaceSubtitle": "Lisboa, PT",
        "moreInfoLink": "https://www.youtube.com/watch?v=dQw4w9WgXcQ",
        "startTime": "10:00",
        "endTime": "11:00"
      },
      {
        "day": 8,
        "month": "outubro",
        "imageSrc": "image2.png",
        "altText": "Image 3 mobile",
        "descriptionTitle": "Job Insights 3",
        "descriptionSubtitle": "Terça Feira, 27 de Outubro às 13:00",
        "logoSrc": "image4logo.png",
        "logoAlt": "ImageLogo 4 mobile",
        "oppPlaceTitle": "AE IST",
        "oppPlaceSubtitle": "Lisboa, PT",
        "moreInfoLink": "https://www.youtube.com/watch?v=dQw4w9WgXcQ",
        "startTime": "10:00",
        "endTime": "11:30"
      },
      {
        "day": 8,
        "month": "outubro",
        "imageSrc": "image4.png",
        "altText": "Image 4 mobile",
        "descriptionTitle": "Job Insights 4",
        "descriptionSubtitle": "Terça Feira, 27 de Outubro às 13:00",
        "logoSrc": "image4logo.png",
        "logoAlt": "ImageLogo 4 mobile",
        "oppPlaceTitle": "AE IST",
        "oppPlaceSubtitle": "Lisboa, PT",
        "moreInfoLink": "https://www.youtube.com/watch?v=dQw4w9WgXcQ",
        "startTime": "10:00",
        "endTime": "10:59"
      },
      {
        "day": 2,
        "month": "outubro",
        "imageSrc": "image1.png",
        "altText": "Image 1 mobile",
        "descriptionTitle": "Job Insights 1",
        "descriptionSubtitle": "Terça Feira, 27 de Outubro às 13:00",
        "logoSrc": "image1logo.png",
        "logoAlt": "ImageLogo 1 mobile",
        "oppPlaceTitle": "AE IST",
        "oppPlaceSubtitle": "Lisboa, PT",
        "moreInfoLink": "https://www.youtube.com/watch?v=dQw4w9WgXcQ",
        "startTime": "5:00",
        "endTime": "12:00"
      },
      {
        "day": 3,
        "month": "outubro",
        "imageSrc": "image1.png",
        "altText": "Image 1 mobile",
        "descriptionTitle": "Job Insights 1",
        "descriptionSubtitle": "Terça Feira, 27 de Outubro às 13:00",
        "logoSrc": "image1logo.png",
        "logoAlt": "ImageLogo 1 mobile",
        "oppPlaceTitle": "AE IST",
        "oppPlaceSubtitle": "Lisboa, PT",
        "moreInfoLink": "https://www.youtube.com/watch?v=dQw4w9WgXcQ",
        "startTime": "13:00",
        "endTime": "14:00"
      },
      {
        "day": 7,
        "month": "outubro",
        "imageSrc": "image1.png",
        "altText": "Image 1 mobile",
        "descriptionTitle": "Job Insights 1",
        "descriptionSubtitle": "Terça Feira, 27 de Outubro às 13:00",
        "logoSrc": "image1logo.png",
        "logoAlt": "ImageLogo 1 mobile",
        "oppPlaceTitle": "AE IST",
        "oppPlaceSubtitle": "Lisboa, PT",
        "moreInfoLink": "https://www.youtube.com/watch?v=dQw4w9WgXcQ",
        "startTime": "10:00",
        "endTime": "12:00"
      },
      {
        "day": 8,
        "month": "outubro",
        "imageSrc": "image1.png",
        "altText": "Image 1 mobile",
        "descriptionTitle": "Job Insights 1",
        "descriptionSubtitle": "Terça Feira, 27 de Outubro às 13:00",
        "logoSrc": "image1logo.png",
        "logoAlt": "ImageLogo 1 mobile",
        "oppPlaceTitle": "AE IST",
        "oppPlaceSubtitle": "Lisboa, PT",
        "moreInfoLink": "https://www.youtube.com/watch?v=dQw4w9WgXcQ",
        "startTime": "13:00",
        "endTime": "15:00"
      },
      {
        "day": 9,
        "month": "outubro",
        "imageSrc": "image1.png",
        "altText": "Image 1 mobile",
        "descriptionTitle": "Job Insights 1",
        "descriptionSubtitle": "Terça Feira, 27 de Outubro às 13:00",
        "logoSrc": "image1logo.png",
        "logoAlt": "ImageLogo 1 mobile",
        "oppPlaceTitle": "AE IST",
        "oppPlaceSubtitle": "Lisboa, PT",
        "moreInfoLink": "https://www.youtube.com/watch?v=dQw4w9WgXcQ",
        "startTime": "10:00",
        "endTime": "12:00"
      },
      {
        "day": 10,
        "month": "outubro",
        "imageSrc": "image1.png",
        "altText": "Image 1 mobile",
        "descriptionTitle": "Job Insights 1",
        "descriptionSubtitle": "Terça Feira, 27 de Outubro às 13:00",
        "logoSrc": "image1logo.png",
        "logoAlt": "ImageLogo 1 mobile",
        "oppPlaceTitle": "AE IST",
        "oppPlaceSubtitle": "Lisboa, PT",
        "moreInfoLink": "https://www.youtube.com/watch?v=dQw4w9WgXcQ",
        "startTime": "10:00",
        "endTime": "12:00"
      },
      {
        "day": 3,
        "month": "novembro",
        "imageSrc": "image1.png",
        "altText": "Image 1 mobile",
        "descriptionTitle": "Job Insights 1",
        "descriptionSubtitle": "Terça Feira, 27 de Outubro às 13:00",
        "logoSrc": "image1logo.png",
        "logoAlt": "ImageLogo 1 mobile",
        "oppPlaceTitle": "AE IST",
        "oppPlaceSubtitle": "Lisboa, PT",
        "moreInfoLink": "https://www.youtube.com/watch?v=dQw4w9WgXcQ",
        "startTime": "10:00",
        "endTime": "12:00"
      },
      {
        "day": 12,
        "month": "outubro",
        "imageSrc": "image2.png",
        "altText": "Image 1 mobile",
        "descriptionTitle": "Job Insights 1",
        "descriptionSubtitle": "Terça Feira, 27 de Outubro às 13:00",
        "logoSrc": "image1logo.png",
        "logoAlt": "ImageLogo 1 mobile",
        "oppPlaceTitle": "AE IST",
        "oppPlaceSubtitle": "Lisboa, PT",
        "moreInfoLink": "https://www.youtube.com/watch?v=dQw4w9WgXcQ",
        "startTime": "10:00",
        "endTime": "12:00"
      },
      {
        "day": 12,
        "month": "outubro",
        "imageSrc": "image4.png",
        "altText": "Image 1 mobile",
        "descriptionTitle": "Job Insights 1",
        "descriptionSubtitle": "Terça Feira, 27 de Outubro às 13:00",
        "logoSrc": "image1logo.png",
        "logoAlt": "ImageLogo 1 mobile",
        "oppPlaceTitle": "AE IST",
        "oppPlaceSubtitle": "Lisboa, PT",
        "moreInfoLink": "https://www.youtube.com/watch?v=dQw4w9WgXcQ",
        "startTime": "10:00",
        "endTime": "12:00"
      },
      {
        "day": 12,
        "month": "outubro",
        "imageSrc": "image4.png",
        "altText": "Image 1 mobile",
        "descriptionTitle": "Job Insights 1",
        "descriptionSubtitle": "Terça Feira, 27 de Outubro às 13:00",
        "logoSrc": "image1logo.png",
        "logoAlt": "ImageLogo 1 mobile",
        "oppPlaceTitle": "AE IST",
        "oppPlaceSubtitle": "Lisboa, PT",
        "moreInfoLink": "https://www.youtube.com/watch?v=dQw4w9WgXcQ",
        "startTime": "10:00",
        "endTime": "12:00"
      },
      {
        "day": 12,
        "month": "outubro",
        "imageSrc": "image4.png",
        "altText": "Image 1 mobile",
        "descriptionTitle": "Job Insights 1",
        "descriptionSubtitle": "Terça Feira, 27 de Outubro às 13:00",
        "logoSrc": "image1logo.png",
        "logoAlt": "ImageLogo 1 mobile",
        "oppPlaceTitle": "AE IST",
        "oppPlaceSubtitle": "Lisboa, PT",
        "moreInfoLink": "https://www.youtube.com/watch?v=dQw4w9WgXcQ",
        "startTime": "10:00",
        "endTime": "12:00"
      },
      {
        "day": 12,
        "month": "outubro",
        "imageSrc": "image4.png",
        "altText": "Image 1 mobile",
        "descriptionTitle": "Job Insights 1",
        "descriptionSubtitle": "Terça Feira, 27 de Outubro às 13:00",
        "logoSrc": "image1logo.png",
        "logoAlt": "ImageLogo 1 mobile",
        "oppPlaceTitle": "AE IST",
        "oppPlaceSubtitle": "Lisboa, PT",
        "moreInfoLink": "https://www.youtube.com/watch?v=dQw4w9WgXcQ",
        "startTime": "10:00",
        "endTime": "12:00"
      },
      {
        "day": 12,
        "month": "outubro",
        "imageSrc": "image3.png",
        "altText": "Image 1 mobile",
        "descriptionTitle": "Job Insights 1",
        "descriptionSubtitle": "Terça Feira, 27 de Outubro às 13:00",
        "logoSrc": "image1logo.png",
        "logoAlt": "ImageLogo 1 mobile",
        "oppPlaceTitle": "AE IST",
        "oppPlaceSubtitle": "Lisboa, PT",
        "moreInfoLink": "https://www.youtube.com/watch?v=dQw4w9WgXcQ",
        "startTime": "10:00",
        "endTime": "12:00"
      },
      {
        "day": 12,
        "month": "outubro",
        "imageSrc": "image3.png",
        "altText": "Image 1 mobile",
        "descriptionTitle": "Job Insights 1",
        "descriptionSubtitle": "Terça Feira, 27 de Outubro às 13:00",
        "logoSrc": "image1logo.png",
        "logoAlt": "ImageLogo 1 mobile",
        "oppPlaceTitle": "AE IST",
        "oppPlaceSubtitle": "Lisboa, PT",
        "moreInfoLink": "https://www.youtube.com/watch?v=dQw4w9WgXcQ",
        "startTime": "10:00",
        "endTime": "12:00"
      },
      {
        "day": 12,
        "month": "outubro",
        "imageSrc": "image3.png",
        "altText": "Image 1 mobile",
        "descriptionTitle": "Job Insights 1",
        "descriptionSubtitle": "Terça Feira, 27 de Outubro às 13:00",
        "logoSrc": "image1logo.png",
        "logoAlt": "ImageLogo 1 mobile",
        "oppPlaceTitle": "AE IST",
        "oppPlaceSubtitle": "Lisboa, PT",
        "moreInfoLink": "https://www.youtube.com/watch?v=dQw4w9WgXcQ",
        "startTime": "10:00",
        "endTime": "12:00"
      },
      {
        "day": 12,
        "month": "outubro",
        "imageSrc": "image1.png",
        "altText": "Image 1 mobile",
        "descriptionTitle": "Job Insights 1",
        "descriptionSubtitle": "Terça Feira, 27 de Outubro às 13:00",
        "logoSrc": "image1logo.png",
        "logoAlt": "ImageLogo 1 mobile",
        "oppPlaceTitle": "AE IST",
        "oppPlaceSubtitle": "Lisboa, PT",
        "moreInfoLink": "https://www.youtube.com/watch?v=dQw4w9WgXcQ",
        "startTime": "10:00",
        "endTime": "12:00"
      }
      
    ]
  }
  